ecourbissp/__init__.py
ecourbissp/ecourbissp.py
ecourbissp-0.0.1.dist-info/METADATA
ecourbissp-0.0.1.dist-info/WHEEL
ecourbissp-0.0.1.dist-info/top_level.txt
ecourbissp-0.0.1.dist-info/RECORD
